demo/demo/__init__.py
demo/demo/models.py
demo/demo/urls.py
demo/demo/views.py
django_gate2shop-1.0.2.dist-info/DESCRIPTION.rst
django_gate2shop-1.0.2.dist-info/METADATA
django_gate2shop-1.0.2.dist-info/metadata.json
django_gate2shop-1.0.2.dist-info/RECORD
django_gate2shop-1.0.2.dist-info/top_level.txt
django_gate2shop-1.0.2.dist-info/WHEEL
g2s/__init__.py
g2s/admin.py
g2s/defaults.py
g2s/fields.py
g2s/forms.py
g2s/models.py
g2s/signals.py
g2s/urls.py
g2s/views.py
g2s/migrations/0001_initial.py
g2s/migrations/0002_auto__chg_field_g2stransaction_Error__chg_field_g2stransaction_AuthCod.py
g2s/migrations/0003_auto__chg_field_g2stransaction_dynamicDescriptor__chg_field_g2stransac.py
g2s/migrations/__init__.py
