Metadata-Version: 2.0
Name: django-gate2shop
Version: 1.0.2
Summary: Gate2Shop gateway for accept payments on your website.
Home-page: https://github.com/gotlium/django-gate2shop
Author: GoTLiuM InSPiRiT
Author-email: gotlium@gmail.com
License: UNKNOWN
Keywords: payment django g2s gate2shop
Platform: UNKNOWN
Classifier: Development Status :: 5 - Production/Stable
Classifier: Environment :: Web Environment
Classifier: Framework :: Django
Classifier: Intended Audience :: Developers
Classifier: Natural Language :: English
Classifier: License :: OSI Approved :: GNU General Public License (GPL)
Classifier: Operating System :: POSIX :: Linux
Classifier: Programming Language :: Python :: 2.6
Classifier: Programming Language :: Python :: 2.7
Classifier: Programming Language :: Python
Requires-Dist: Django (>=1.4)
